pyffect/__init__.py
pyffect/_types.py
pyffect/either.py
pyffect/option.py
pyffect/unit.py
pyffect-0.0.3.dist-info/LICENSE
pyffect-0.0.3.dist-info/METADATA
pyffect-0.0.3.dist-info/WHEEL
pyffect-0.0.3.dist-info/top_level.txt
pyffect-0.0.3.dist-info/RECORD
