Metadata-Version: 2.2
Name: pyffect
Version: 0.0.3
Summary: A small package for effect type in python
Home-page: https://github.com/aknay/pyffect
Author: Nay Aung Kyaw
Author-email: aknay@outlook.com
Project-URL: Bug Tracker, https://github.com/aknay/pyffect/issues
Classifier: Programming Language :: Python :: 3
Classifier: License :: OSI Approved :: MIT License
Classifier: Operating System :: OS Independent
Requires-Python: >=3.8
License-File: LICENSE
Dynamic: author
Dynamic: author-email
Dynamic: classifier
Dynamic: description
Dynamic: description-content-type
Dynamic: home-page
Dynamic: project-url
Dynamic: requires-python
Dynamic: summary
